icdcodex/__init__.py
icdcodex/datacleaning.py
icdcodex/hierarchy.py
icdcodex/icd2vec.py
icdcodex/data/__init__.py
icdcodex/data/icd-10-2019-hierarchy.json
icdcodex/data/icd-10-2020-hierarchy.json
icdcodex/data/icd-10-2021-hierarchy.json
icdcodex/data/icd-10-2022-hierarchy.json
icdcodex/data/icd-10-2023-hierarchy.json
icdcodex/data/icd-10-2024-hierarchy.json
icdcodex/data/icd-10-2025-hierarchy.json
icdcodex/data/icd-9-hierarchy.json
icdcodex-0.5.2.dist-info/LICENSE
icdcodex-0.5.2.dist-info/METADATA
icdcodex-0.5.2.dist-info/WHEEL
icdcodex-0.5.2.dist-info/top_level.txt
icdcodex-0.5.2.dist-info/zip-safe
icdcodex-0.5.2.dist-info/RECORD
