Metadata-Version: 2.1
Name: icdcodex
Version: 0.5.2
Summary: graphical and continuous representations of ICD-9 and ICD-10 codes
Home-page: https://github.com/icd-codex/icd-codex
Author: Jeremy Fisher
Author-email: jeremy@adamsfisher.me
License: MIT license
Keywords: icdcodex
Classifier: Intended Audience :: Developers
Classifier: License :: OSI Approved :: MIT License
Classifier: Natural Language :: English
License-File: LICENSE
Requires-Dist: networkx
Requires-Dist: node2vec
Requires-Dist: untangle
Requires-Dist: scikit-learn
Requires-Dist: pandas
Requires-Dist: requests
